test_pablo_martin_poetry/__init__.py
test_pablo_martin_poetry-0.1.0.dist-info/WHEEL
test_pablo_martin_poetry-0.1.0.dist-info/METADATA
test_pablo_martin_poetry-0.1.0.dist-info/RECORD
